[
  {
    "country": "Belgie",
    "data": [
      {
        "Rok": 2002,
        "Hodnota": 6993.0
      },
      {
        "Rok": 2003,
        "Hodnota": 7808.0
      },
      {
        "Rok": 2004,
        "Hodnota": 7936.0
      },
      {
        "Rok": 2005,
        "Hodnota": 7928.0
      },
      {
        "Rok": 2006,
        "Hodnota": 8182.0
      },
      {
        "Rok": 2007,
        "Hodnota": 8380.0
      },
      {
        "Rok": 2008,
        "Hodnota": 8650.0
      },
      {
        "Rok": 2009,
        "Hodnota": 6791.0
      },
      {
        "Rok": 2010,
        "Hodnota": 7583.0
      },
      {
        "Rok": 2011,
        "Hodnota": 7889.0
      },
      {
        "Rok": 2012,
        "Hodnota": 7404.0
      },
      {
        "Rok": 2013,
        "Hodnota": 7753.0
      },
      {
        "Rok": 2014,
        "Hodnota": 8056.0
      },
      {
        "Rok": 2015,
        "Hodnota": 8457.0
      },
      {
        "Rok": 2016,
        "Hodnota": 8520.0
      },
      {
        "Rok": 2017,
        "Hodnota": 8915.0
      },
      {
        "Rok": 2018,
        "Hodnota": 9127.0
      },
      {
        "Rok": 2019,
        "Hodnota": 8786.0
      },
      {
        "Rok": 2020,
        "Hodnota": 8213.0
      },
      {
        "Rok": 2021,
        "Hodnota": 8311.0
      },
      {
        "Rok": 2022,
        "Hodnota": 9937.0
      },
      {
        "Rok": 2023,
        "Hodnota": 8659.0
      },
      {
        "Rok": 2024,
        "Hodnota": 7999.0
      }
    ]
  },
  {
    "country": "Bulharsko",
    "data": [
      {
        "Rok": 2002,
        "Hodnota": 2580.0
      },
      {
        "Rok": 2003,
        "Hodnota": 2966.0
      },
      {
        "Rok": 2004,
        "Hodnota": 2659.0
      },
      {
        "Rok": 2005,
        "Hodnota": 1863.0
      },
      {
        "Rok": 2006,
        "Hodnota": 3140.0
      },
      {
        "Rok": 2007,
        "Hodnota": 3127.0
      },
      {
        "Rok": 2008,
        "Hodnota": 3040.0
      },
      {
        "Rok": 2009,
        "Hodnota": 2313.0
      },
      {
        "Rok": 2010,
        "Hodnota": 2250.0
      },
      {
        "Rok": 2011,
        "Hodnota": 2341.0
      },
      {
        "Rok": 2012,
        "Hodnota": 2249.0
      },
      {
        "Rok": 2013,
        "Hodnota": 2254.0
      },
      {
        "Rok": 2014,
        "Hodnota": 2509.0
      },
      {
        "Rok": 2015,
        "Hodnota": 2618.0
      },
      {
        "Rok": 2016,
        "Hodnota": 2676.0
      },
      {
        "Rok": 2017,
        "Hodnota": 2848.0
      },
      {
        "Rok": 2018,
        "Hodnota": 2627.0
      },
      {
        "Rok": 2019,
        "Hodnota": 2820.0
      },
      {
        "Rok": 2020,
        "Hodnota": 2565.0
      },
      {
        "Rok": 2021,
        "Hodnota": 2637.0
      },
      {
        "Rok": 2022,
        "Hodnota": 3400.0
      },
      {
        "Rok": 2023,
        "Hodnota": 2867.0
      },
      {
        "Rok": 2024,
        "Hodnota": 2950.0
      }
    ]
  },
  {
    "country": "Česko",
    "data": [
      {
        "Rok": 2002,
        "Hodnota": 2115.0
      },
      {
        "Rok": 2003,
        "Hodnota": 2262.0
      },
      {
        "Rok": 2004,
        "Hodnota": 2095.0
      },
      {
        "Rok": 2005,
        "Hodnota": 2133.0
      },
      {
        "Rok": 2006,
        "Hodnota": 2239.0
      },
      {
        "Rok": 2007,
        "Hodnota": 2108.0
      },
      {
        "Rok": 2008,
        "Hodnota": 2391.0
      },
      {
        "Rok": 2009,
        "Hodnota": 1863.0
      },
      {
        "Rok": 2010,
        "Hodnota": 2203.0
      },
      {
        "Rok": 2011,
        "Hodnota": 2209.0
      },
      {
        "Rok": 2012,
        "Hodnota": 1914.0
      },
      {
        "Rok": 2013,
        "Hodnota": 1963.0
      },
      {
        "Rok": 2014,
        "Hodnota": 1949.0
      },
      {
        "Rok": 2015,
        "Hodnota": 1921.0
      },
      {
        "Rok": 2016,
        "Hodnota": 1682.0
      },
      {
        "Rok": 2017,
        "Hodnota": 1741.0
      },
      {
        "Rok": 2018,
        "Hodnota": 1823.0
      },
      {
        "Rok": 2019,
        "Hodnota": 1886.0
      },
      {
        "Rok": 2020,
        "Hodnota": 1683.0
      },
      {
        "Rok": 2021,
        "Hodnota": 1815.0
      },
      {
        "Rok": 2022,
        "Hodnota": 1713.0
      },
      {
        "Rok": 2023,
        "Hodnota": 1591.0
      },
      {
        "Rok": 2024,
        "Hodnota": 1357.0
      }
    ]
  },
  {
    "country": "Dánsko",
    "data": [
      {
        "Rok": 2002,
        "Hodnota": 3393.0
      },
      {
        "Rok": 2003,
        "Hodnota": 4174.0
      },
      {
        "Rok": 2004,
        "Hodnota": 3975.0
      },
      {
        "Rok": 2005,
        "Hodnota": 3595.0
      },
      {
        "Rok": 2006,
        "Hodnota": 4187.0
      },
      {
        "Rok": 2007,
        "Hodnota": 4200.0
      },
      {
        "Rok": 2008,
        "Hodnota": 4203.0
      },
      {
        "Rok": 2009,
        "Hodnota": 3700.0
      },
      {
        "Rok": 2010,
        "Hodnota": 3371.0
      },
      {
        "Rok": 2011,
        "Hodnota": 4134.0
      },
      {
        "Rok": 2012,
        "Hodnota": 3776.0
      },
      {
        "Rok": 2013,
        "Hodnota": 4040.0
      },
      {
        "Rok": 2014,
        "Hodnota": 4144.0
      },
      {
        "Rok": 2015,
        "Hodnota": 3885.0
      },
      {
        "Rok": 2016,
        "Hodnota": 3872.0
      },
      {
        "Rok": 2017,
        "Hodnota": 4064.0
      },
      {
        "Rok": 2018,
        "Hodnota": 4256.0
      },
      {
        "Rok": 2019,
        "Hodnota": 4150.0
      },
      {
        "Rok": 2020,
        "Hodnota": 3844.0
      },
      {
        "Rok": 2021,
        "Hodnota": 3873.0
      },
      {
        "Rok": 2022,
        "Hodnota": 4165.0
      },
      {
        "Rok": 2023,
        "Hodnota": 3814.0
      },
      {
        "Rok": 2024,
        "Hodnota": 4138.0
      }
    ]
  },
  {
    "country": "Německo",
    "data": [
      {
        "Rok": 2002,
        "Hodnota": 2873.0
      },
      {
        "Rok": 2003,
        "Hodnota": 3109.0
      },
      {
        "Rok": 2004,
        "Hodnota": 3102.0
      },
      {
        "Rok": 2005,
        "Hodnota": 3113.0
      },
      {
        "Rok": 2006,
        "Hodnota": 3265.0
      },
      {
        "Rok": 2007,
        "Hodnota": 3242.0
      },
      {
        "Rok": 2008,
        "Hodnota": 3272.0
      },
      {
        "Rok": 2009,
        "Hodnota": 2908.0
      },
      {
        "Rok": 2010,
        "Hodnota": 2961.0
      },
      {
        "Rok": 2011,
        "Hodnota": 3135.0
      },
      {
        "Rok": 2012,
        "Hodnota": 2875.0
      },
      {
        "Rok": 2013,
        "Hodnota": 2873.0
      },
      {
        "Rok": 2014,
        "Hodnota": 2912.0
      },
      {
        "Rok": 2015,
        "Hodnota": 3003.0
      },
      {
        "Rok": 2016,
        "Hodnota": 3096.0
      },
      {
        "Rok": 2017,
        "Hodnota": 2956.0
      },
      {
        "Rok": 2018,
        "Hodnota": 2905.0
      },
      {
        "Rok": 2019,
        "Hodnota": 2847.0
      },
      {
        "Rok": 2020,
        "Hodnota": 2658.0
      },
      {
        "Rok": 2021,
        "Hodnota": 2681.0
      },
      {
        "Rok": 2022,
        "Hodnota": 2564.0
      },
      {
        "Rok": 2023,
        "Hodnota": 2118.0
      },
      {
        "Rok": 2024,
        "Hodnota": 2123.0
      }
    ]
  },
  {
    "country": "Estonsko",
    "data": [
      {
        "Rok": 2002,
        "Hodnota": 2351.0
      },
      {
        "Rok": 2003,
        "Hodnota": 3421.0
      },
      {
        "Rok": 2004,
        "Hodnota": 3980.0
      },
      {
        "Rok": 2005,
        "Hodnota": 3394.0
      },
      {
        "Rok": 2006,
        "Hodnota": 4375.0
      },
      {
        "Rok": 2007,
        "Hodnota": 4000.0
      },
      {
        "Rok": 2008,
        "Hodnota": 2447.0
      },
      {
        "Rok": 2009,
        "Hodnota": 2335.0
      },
      {
        "Rok": 2010,
        "Hodnota": 2500.0
      },
      {
        "Rok": 2011,
        "Hodnota": 2981.0
      },
      {
        "Rok": 2012,
        "Hodnota": 2718.0
      },
      {
        "Rok": 2013,
        "Hodnota": 2268.0
      },
      {
        "Rok": 2014,
        "Hodnota": 2321.0
      },
      {
        "Rok": 2015,
        "Hodnota": 2277.0
      },
      {
        "Rok": 2016,
        "Hodnota": 2745.0
      },
      {
        "Rok": 2017,
        "Hodnota": 3133.0
      },
      {
        "Rok": 2018,
        "Hodnota": 4682.0
      },
      {
        "Rok": 2019,
        "Hodnota": 4137.0
      },
      {
        "Rok": 2020,
        "Hodnota": 4579.0
      },
      {
        "Rok": 2021,
        "Hodnota": 5871.0
      },
      {
        "Rok": 2022,
        "Hodnota": 3156.0
      },
      {
        "Rok": 2023,
        "Hodnota": 1185.0
      },
      {
        "Rok": 2024,
        "Hodnota": 924.0
      }
    ]
  },
  {
    "country": "Irsko",
    "data": [
      {
        "Rok": 2002,
        "Hodnota": 4450.0
      },
      {
        "Rok": 2003,
        "Hodnota": 4429.0
      },
      {
        "Rok": 2004,
        "Hodnota": 4883.0
      },
      {
        "Rok": 2005,
        "Hodnota": 5325.0
      },
      {
        "Rok": 2006,
        "Hodnota": 5246.0
      },
      {
        "Rok": 2007,
        "Hodnota": 5796.0
      },
      {
        "Rok": 2008,
        "Hodnota": 5272.0
      },
      {
        "Rok": 2009,
        "Hodnota": 4647.0
      },
      {
        "Rok": 2010,
        "Hodnota": 5204.0
      },
      {
        "Rok": 2011,
        "Hodnota": 5164.0
      },
      {
        "Rok": 2012,
        "Hodnota": 5130.0
      },
      {
        "Rok": 2013,
        "Hodnota": 5389.0
      },
      {
        "Rok": 2014,
        "Hodnota": 5523.0
      },
      {
        "Rok": 2015,
        "Hodnota": 5912.0
      },
      {
        "Rok": 2016,
        "Hodnota": 5744.0
      },
      {
        "Rok": 2017,
        "Hodnota": 5931.0
      },
      {
        "Rok": 2018,
        "Hodnota": 6276.0
      },
      {
        "Rok": 2019,
        "Hodnota": 5942.0
      },
      {
        "Rok": 2020,
        "Hodnota": 5678.0
      },
      {
        "Rok": 2021,
        "Hodnota": 5809.0
      },
      {
        "Rok": 2022,
        "Hodnota": 6267.0
      },
      {
        "Rok": 2023,
        "Hodnota": 5733.0
      },
      {
        "Rok": 2024,
        "Hodnota": 5736.0
      }
    ]
  },
  {
    "country": "Řecko",
    "data": [
      {
        "Rok": 2002,
        "Hodnota": 3178.0
      },
      {
        "Rok": 2003,
        "Hodnota": 3360.0
      },
      {
        "Rok": 2004,
        "Hodnota": 3360.0
      },
      {
        "Rok": 2005,
        "Hodnota": 3396.0
      },
      {
        "Rok": 2006,
        "Hodnota": 3504.0
      },
      {
        "Rok": 2007,
        "Hodnota": 3790.0
      },
      {
        "Rok": 2008,
        "Hodnota": 3947.0
      },
      {
        "Rok": 2009,
        "Hodnota": 3474.0
      },
      {
        "Rok": 2010,
        "Hodnota": 3464.0
      },
      {
        "Rok": 2011,
        "Hodnota": 3220.0
      },
      {
        "Rok": 2012,
        "Hodnota": 3259.0
      },
      {
        "Rok": 2013,
        "Hodnota": 3321.0
      },
      {
        "Rok": 2014,
        "Hodnota": 3444.0
      },
      {
        "Rok": 2015,
        "Hodnota": 3692.0
      },
      {
        "Rok": 2016,
        "Hodnota": 3975.0
      },
      {
        "Rok": 2017,
        "Hodnota": 4068.0
      },
      {
        "Rok": 2018,
        "Hodnota": 4337.0
      },
      {
        "Rok": 2019,
        "Hodnota": 4177.0
      },
      {
        "Rok": 2020,
        "Hodnota": 4122.0
      },
      {
        "Rok": 2021,
        "Hodnota": 4454.0
      },
      {
        "Rok": 2022,
        "Hodnota": 4538.0
      },
      {
        "Rok": 2023,
        "Hodnota": 4541.0
      },
      {
        "Rok": 2024,
        "Hodnota": 4794.0
      }
    ]
  },
  {
    "country": "Španělsko",
    "data": [
      {
        "Rok": 2002,
        "Hodnota": 3528.0
      },
      {
        "Rok": 2003,
        "Hodnota": 3519.0
      },
      {
        "Rok": 2004,
        "Hodnota": 3743.0
      },
      {
        "Rok": 2005,
        "Hodnota": 4000.0
      },
      {
        "Rok": 2006,
        "Hodnota": 4090.0
      },
      {
        "Rok": 2007,
        "Hodnota": 4248.0
      },
      {
        "Rok": 2008,
        "Hodnota": 4083.0
      },
      {
        "Rok": 2009,
        "Hodnota": 3323.0
      },
      {
        "Rok": 2010,
        "Hodnota": 3308.0
      },
      {
        "Rok": 2011,
        "Hodnota": 3375.0
      },
      {
        "Rok": 2012,
        "Hodnota": 3463.0
      },
      {
        "Rok": 2013,
        "Hodnota": 3320.0
      },
      {
        "Rok": 2014,
        "Hodnota": 3507.0
      },
      {
        "Rok": 2015,
        "Hodnota": 3666.0
      },
      {
        "Rok": 2016,
        "Hodnota": 3477.0
      },
      {
        "Rok": 2017,
        "Hodnota": 3834.0
      },
      {
        "Rok": 2018,
        "Hodnota": 3852.0
      },
      {
        "Rok": 2019,
        "Hodnota": 3726.0
      },
      {
        "Rok": 2020,
        "Hodnota": 3129.0
      },
      {
        "Rok": 2021,
        "Hodnota": 3373.0
      },
      {
        "Rok": 2022,
        "Hodnota": 3679.0
      },
      {
        "Rok": 2023,
        "Hodnota": 3346.0
      },
      {
        "Rok": 2024,
        "Hodnota": 3429.0
      }
    ]
  },
  {
    "country": "Francie",
    "data": [
      {
        "Rok": 2002,
        "Hodnota": 2856.0
      },
      {
        "Rok": 2003,
        "Hodnota": 2886.0
      },
      {
        "Rok": 2004,
        "Hodnota": 3020.0
      },
      {
        "Rok": 2005,
        "Hodnota": 2699.0
      },
      {
        "Rok": 2006,
        "Hodnota": 2719.0
      },
      {
        "Rok": 2007,
        "Hodnota": 2768.0
      },
      {
        "Rok": 2008,
        "Hodnota": 2755.0
      },
      {
        "Rok": 2009,
        "Hodnota": 2347.0
      },
      {
        "Rok": 2010,
        "Hodnota": 2370.0
      },
      {
        "Rok": 2011,
        "Hodnota": 2384.0
      },
      {
        "Rok": 2012,
        "Hodnota": 2250.0
      },
      {
        "Rok": 2013,
        "Hodnota": 2236.0
      },
      {
        "Rok": 2014,
        "Hodnota": 2201.0
      },
      {
        "Rok": 2015,
        "Hodnota": 2217.0
      },
      {
        "Rok": 2016,
        "Hodnota": 2177.0
      },
      {
        "Rok": 2017,
        "Hodnota": 2310.0
      },
      {
        "Rok": 2018,
        "Hodnota": 2277.0
      },
      {
        "Rok": 2019,
        "Hodnota": 2290.0
      },
      {
        "Rok": 2020,
        "Hodnota": 1902.0
      },
      {
        "Rok": 2021,
        "Hodnota": 2005.0
      },
      {
        "Rok": 2022,
        "Hodnota": 2245.0
      },
      {
        "Rok": 2023,
        "Hodnota": 2065.0
      },
      {
        "Rok": 2024,
        "Hodnota": 2049.0
      }
    ]
  },
  {
    "country": "Chorvatsko",
    "data": [
      {
        "Rok": 2002,
        "Hodnota": 2149.0
      },
      {
        "Rok": 2003,
        "Hodnota": 2273.0
      },
      {
        "Rok": 2004,
        "Hodnota": 2734.0
      },
      {
        "Rok": 2005,
        "Hodnota": 3380.0
      },
      {
        "Rok": 2006,
        "Hodnota": 3423.0
      },
      {
        "Rok": 2007,
        "Hodnota": 3839.0
      },
      {
        "Rok": 2008,
        "Hodnota": 3650.0
      },
      {
        "Rok": 2009,
        "Hodnota": 2672.0
      },
      {
        "Rok": 2010,
        "Hodnota": 2449.0
      },
      {
        "Rok": 2011,
        "Hodnota": 2255.0
      },
      {
        "Rok": 2012,
        "Hodnota": 2085.0
      },
      {
        "Rok": 2013,
        "Hodnota": 2142.0
      },
      {
        "Rok": 2014,
        "Hodnota": 1819.0
      },
      {
        "Rok": 2015,
        "Hodnota": 2069.0
      },
      {
        "Rok": 2016,
        "Hodnota": 2232.0
      },
      {
        "Rok": 2017,
        "Hodnota": 2183.0
      },
      {
        "Rok": 2018,
        "Hodnota": 2098.0
      },
      {
        "Rok": 2019,
        "Hodnota": 2151.0
      },
      {
        "Rok": 2020,
        "Hodnota": 2534.0
      },
      {
        "Rok": 2021,
        "Hodnota": 2840.0
      },
      {
        "Rok": 2022,
        "Hodnota": 2730.0
      },
      {
        "Rok": 2023,
        "Hodnota": 2710.0
      },
      {
        "Rok": 2024,
        "Hodnota": 3218.0
      }
    ]
  },
  {
    "country": "Itálie",
    "data": [
      {
        "Rok": 2002,
        "Hodnota": 4023.0
      },
      {
        "Rok": 2003,
        "Hodnota": 4180.0
      },
      {
        "Rok": 2004,
        "Hodnota": 4365.0
      },
      {
        "Rok": 2005,
        "Hodnota": 4406.0
      },
      {
        "Rok": 2006,
        "Hodnota": 4513.0
      },
      {
        "Rok": 2007,
        "Hodnota": 4535.0
      },
      {
        "Rok": 2008,
        "Hodnota": 4366.0
      },
      {
        "Rok": 2009,
        "Hodnota": 3615.0
      },
      {
        "Rok": 2010,
        "Hodnota": 4009.0
      },
      {
        "Rok": 2011,
        "Hodnota": 3832.0
      },
      {
        "Rok": 2012,
        "Hodnota": 3566.0
      },
      {
        "Rok": 2013,
        "Hodnota": 3279.0
      },
      {
        "Rok": 2014,
        "Hodnota": 3087.0
      },
      {
        "Rok": 2015,
        "Hodnota": 3348.0
      },
      {
        "Rok": 2016,
        "Hodnota": 3478.0
      },
      {
        "Rok": 2017,
        "Hodnota": 3566.0
      },
      {
        "Rok": 2018,
        "Hodnota": 3584.0
      },
      {
        "Rok": 2019,
        "Hodnota": 3427.0
      },
      {
        "Rok": 2020,
        "Hodnota": 3033.0
      },
      {
        "Rok": 2021,
        "Hodnota": 3411.0
      },
      {
        "Rok": 2022,
        "Hodnota": 3485.0
      },
      {
        "Rok": 2023,
        "Hodnota": 3266.0
      },
      {
        "Rok": 2024,
        "Hodnota": 3063.0
      }
    ]
  },
  {
    "country": "Kypr",
    "data": [
      {
        "Rok": 2002,
        "Hodnota": 3157.0
      },
      {
        "Rok": 2003,
        "Hodnota": 2336.0
      },
      {
        "Rok": 2004,
        "Hodnota": 2463.0
      },
      {
        "Rok": 2005,
        "Hodnota": 3086.0
      },
      {
        "Rok": 2006,
        "Hodnota": 2895.0
      },
      {
        "Rok": 2007,
        "Hodnota": 3101.0
      },
      {
        "Rok": 2008,
        "Hodnota": 3186.0
      },
      {
        "Rok": 2009,
        "Hodnota": 2582.0
      },
      {
        "Rok": 2010,
        "Hodnota": 2698.0
      },
      {
        "Rok": 2011,
        "Hodnota": 2491.0
      },
      {
        "Rok": 2012,
        "Hodnota": 2043.0
      },
      {
        "Rok": 2013,
        "Hodnota": 1722.0
      },
      {
        "Rok": 2014,
        "Hodnota": 1565.0
      },
      {
        "Rok": 2015,
        "Hodnota": 1968.0
      },
      {
        "Rok": 2016,
        "Hodnota": 2335.0
      },
      {
        "Rok": 2017,
        "Hodnota": 2757.0
      },
      {
        "Rok": 2018,
        "Hodnota": 3031.0
      },
      {
        "Rok": 2019,
        "Hodnota": 2381.0
      },
      {
        "Rok": 2020,
        "Hodnota": 2324.0
      },
      {
        "Rok": 2021,
        "Hodnota": 2686.0
      },
      {
        "Rok": 2022,
        "Hodnota": 2882.0
      },
      {
        "Rok": 2023,
        "Hodnota": 3333.0
      },
      {
        "Rok": 2024,
        "Hodnota": 3968.0
      }
    ]
  },
  {
    "country": "Lotyšsko",
    "data": [
      {
        "Rok": 2002,
        "Hodnota": 1398.0
      },
      {
        "Rok": 2003,
        "Hodnota": 1681.0
      },
      {
        "Rok": 2004,
        "Hodnota": 2573.0
      },
      {
        "Rok": 2005,
        "Hodnota": 3058.0
      },
      {
        "Rok": 2006,
        "Hodnota": 3160.0
      },
      {
        "Rok": 2007,
        "Hodnota": 3308.0
      },
      {
        "Rok": 2008,
        "Hodnota": 2681.0
      },
      {
        "Rok": 2009,
        "Hodnota": 2070.0
      },
      {
        "Rok": 2010,
        "Hodnota": 2391.0
      },
      {
        "Rok": 2011,
        "Hodnota": 2563.0
      },
      {
        "Rok": 2012,
        "Hodnota": 2676.0
      },
      {
        "Rok": 2013,
        "Hodnota": 2666.0
      },
      {
        "Rok": 2014,
        "Hodnota": 2710.0
      },
      {
        "Rok": 2015,
        "Hodnota": 3092.0
      },
      {
        "Rok": 2016,
        "Hodnota": 3024.0
      },
      {
        "Rok": 2017,
        "Hodnota": 2895.0
      },
      {
        "Rok": 2018,
        "Hodnota": 3824.0
      },
      {
        "Rok": 2019,
        "Hodnota": 3773.0
      },
      {
        "Rok": 2020,
        "Hodnota": 3760.0
      },
      {
        "Rok": 2021,
        "Hodnota": 3949.0
      },
      {
        "Rok": 2022,
        "Hodnota": 2993.0
      },
      {
        "Rok": 2023,
        "Hodnota": 2737.0
      },
      {
        "Rok": 2024,
        "Hodnota": 2271.0
      }
    ]
  },
  {
    "country": "Litva",
    "data": [
      {
        "Rok": 2002,
        "Hodnota": 4549.0
      },
      {
        "Rok": 2003,
        "Hodnota": 5252.0
      },
      {
        "Rok": 2004,
        "Hodnota": 5877.0
      },
      {
        "Rok": 2005,
        "Hodnota": 6574.0
      },
      {
        "Rok": 2006,
        "Hodnota": 6116.0
      },
      {
        "Rok": 2007,
        "Hodnota": 5457.0
      },
      {
        "Rok": 2008,
        "Hodnota": 6493.0
      },
      {
        "Rok": 2009,
        "Hodnota": 5430.0
      },
      {
        "Rok": 2010,
        "Hodnota": 6047.0
      },
      {
        "Rok": 2011,
        "Hodnota": 6326.0
      },
      {
        "Rok": 2012,
        "Hodnota": 6189.0
      },
      {
        "Rok": 2013,
        "Hodnota": 6624.0
      },
      {
        "Rok": 2014,
        "Hodnota": 6235.0
      },
      {
        "Rok": 2015,
        "Hodnota": 6870.0
      },
      {
        "Rok": 2016,
        "Hodnota": 7004.0
      },
      {
        "Rok": 2017,
        "Hodnota": 7356.0
      },
      {
        "Rok": 2018,
        "Hodnota": 7441.0
      },
      {
        "Rok": 2019,
        "Hodnota": 8079.0
      },
      {
        "Rok": 2020,
        "Hodnota": 7184.0
      },
      {
        "Rok": 2021,
        "Hodnota": 7294.0
      },
      {
        "Rok": 2022,
        "Hodnota": 6315.0
      },
      {
        "Rok": 2023,
        "Hodnota": 5518.0
      },
      {
        "Rok": 2024,
        "Hodnota": 5591.0
      }
    ]
  },
  {
    "country": "Lucembursko",
    "data": [
      {
        "Rok": 2002,
        "Hodnota": 429.0
      },
      {
        "Rok": 2003,
        "Hodnota": 540.0
      },
      {
        "Rok": 2004,
        "Hodnota": 644.0
      },
      {
        "Rok": 2005,
        "Hodnota": 632.0
      },
      {
        "Rok": 2006,
        "Hodnota": 891.0
      },
      {
        "Rok": 2007,
        "Hodnota": 724.0
      },
      {
        "Rok": 2008,
        "Hodnota": 535.0
      },
      {
        "Rok": 2009,
        "Hodnota": 325.0
      },
      {
        "Rok": 2010,
        "Hodnota": 307.0
      },
      {
        "Rok": 2011,
        "Hodnota": 351.0
      },
      {
        "Rok": 2012,
        "Hodnota": 319.0
      },
      {
        "Rok": 2013,
        "Hodnota": 324.0
      },
      {
        "Rok": 2014,
        "Hodnota": 344.0
      },
      {
        "Rok": 2015,
        "Hodnota": 403.0
      },
      {
        "Rok": 2016,
        "Hodnota": 363.0
      },
      {
        "Rok": 2017,
        "Hodnota": 382.0
      },
      {
        "Rok": 2018,
        "Hodnota": 373.0
      },
      {
        "Rok": 2019,
        "Hodnota": 364.0
      },
      {
        "Rok": 2020,
        "Hodnota": 324.0
      },
      {
        "Rok": 2021,
        "Hodnota": 345.0
      },
      {
        "Rok": 2022,
        "Hodnota": 288.0
      },
      {
        "Rok": 2023,
        "Hodnota": 279.0
      },
      {
        "Rok": 2024,
        "Hodnota": 245.0
      }
    ]
  },
  {
    "country": "Maďarsko",
    "data": [
      {
        "Rok": 2002,
        "Hodnota": 2004.0
      },
      {
        "Rok": 2003,
        "Hodnota": 2178.0
      },
      {
        "Rok": 2004,
        "Hodnota": 2172.0
      },
      {
        "Rok": 2005,
        "Hodnota": 2291.0
      },
      {
        "Rok": 2006,
        "Hodnota": 2304.0
      },
      {
        "Rok": 2007,
        "Hodnota": 2340.0
      },
      {
        "Rok": 2008,
        "Hodnota": 2398.0
      },
      {
        "Rok": 2009,
        "Hodnota": 1755.0
      },
      {
        "Rok": 2010,
        "Hodnota": 1857.0
      },
      {
        "Rok": 2011,
        "Hodnota": 1854.0
      },
      {
        "Rok": 2012,
        "Hodnota": 1694.0
      },
      {
        "Rok": 2013,
        "Hodnota": 1838.0
      },
      {
        "Rok": 2014,
        "Hodnota": 1894.0
      },
      {
        "Rok": 2015,
        "Hodnota": 1709.0
      },
      {
        "Rok": 2016,
        "Hodnota": 1704.0
      },
      {
        "Rok": 2017,
        "Hodnota": 2182.0
      },
      {
        "Rok": 2018,
        "Hodnota": 2415.0
      },
      {
        "Rok": 2019,
        "Hodnota": 2509.0
      },
      {
        "Rok": 2020,
        "Hodnota": 1985.0
      },
      {
        "Rok": 2021,
        "Hodnota": 1898.0
      },
      {
        "Rok": 2022,
        "Hodnota": 1913.0
      },
      {
        "Rok": 2023,
        "Hodnota": 1763.0
      },
      {
        "Rok": 2024,
        "Hodnota": 1722.0
      }
    ]
  },
  {
    "country": "Malta",
    "data": [
      {
        "Rok": 2002,
        "Hodnota": 515.0
      },
      {
        "Rok": 2003,
        "Hodnota": 546.0
      },
      {
        "Rok": 2004,
        "Hodnota": 782.0
      },
      {
        "Rok": 2005,
        "Hodnota": 638.0
      },
      {
        "Rok": 2006,
        "Hodnota": 764.0
      },
      {
        "Rok": 2007,
        "Hodnota": 1511.0
      },
      {
        "Rok": 2008,
        "Hodnota": 1235.0
      },
      {
        "Rok": 2009,
        "Hodnota": 931.0
      },
      {
        "Rok": 2010,
        "Hodnota": 801.0
      },
      {
        "Rok": 2011,
        "Hodnota": 794.0
      },
      {
        "Rok": 2012,
        "Hodnota": 864.0
      },
      {
        "Rok": 2013,
        "Hodnota": 1155.0
      },
      {
        "Rok": 2014,
        "Hodnota": 1728.0
      },
      {
        "Rok": 2015,
        "Hodnota": 1466.0
      },
      {
        "Rok": 2016,
        "Hodnota": 1710.0
      },
      {
        "Rok": 2017,
        "Hodnota": 1999.0
      },
      {
        "Rok": 2018,
        "Hodnota": 1724.0
      },
      {
        "Rok": 2019,
        "Hodnota": 2102.0
      },
      {
        "Rok": 2020,
        "Hodnota": 2252.0
      },
      {
        "Rok": 2021,
        "Hodnota": 1875.0
      },
      {
        "Rok": 2022,
        "Hodnota": 1767.0
      },
      {
        "Rok": 2023,
        "Hodnota": 2005.0
      },
      {
        "Rok": 2024,
        "Hodnota": 2372.0
      }
    ]
  },
  {
    "country": "Nizozemsko",
    "data": [
      {
        "Rok": 2002,
        "Hodnota": 11498.0
      },
      {
        "Rok": 2003,
        "Hodnota": 11953.0
      },
      {
        "Rok": 2004,
        "Hodnota": 12418.0
      },
      {
        "Rok": 2005,
        "Hodnota": 14230.0
      },
      {
        "Rok": 2006,
        "Hodnota": 13878.0
      },
      {
        "Rok": 2007,
        "Hodnota": 14344.0
      },
      {
        "Rok": 2008,
        "Hodnota": 14063.0
      },
      {
        "Rok": 2009,
        "Hodnota": 12687.0
      },
      {
        "Rok": 2010,
        "Hodnota": 14977.0
      },
      {
        "Rok": 2011,
        "Hodnota": 14883.0
      },
      {
        "Rok": 2012,
        "Hodnota": 15807.0
      },
      {
        "Rok": 2013,
        "Hodnota": 15955.0
      },
      {
        "Rok": 2014,
        "Hodnota": 16301.0
      },
      {
        "Rok": 2015,
        "Hodnota": 17282.0
      },
      {
        "Rok": 2016,
        "Hodnota": 17293.0
      },
      {
        "Rok": 2017,
        "Hodnota": 17174.0
      },
      {
        "Rok": 2018,
        "Hodnota": 17546.0
      },
      {
        "Rok": 2019,
        "Hodnota": 17508.0
      },
      {
        "Rok": 2020,
        "Hodnota": 15692.0
      },
      {
        "Rok": 2021,
        "Hodnota": 16991.0
      },
      {
        "Rok": 2022,
        "Hodnota": 17017.0
      },
      {
        "Rok": 2023,
        "Hodnota": 15740.0
      },
      {
        "Rok": 2024,
        "Hodnota": 15927.0
      }
    ]
  },
  {
    "country": "Rakousko",
    "data": [
      {
        "Rok": 2002,
        "Hodnota": 2414.0
      },
      {
        "Rok": 2003,
        "Hodnota": 2418.0
      },
      {
        "Rok": 2004,
        "Hodnota": 2393.0
      },
      {
        "Rok": 2005,
        "Hodnota": 2464.0
      },
      {
        "Rok": 2006,
        "Hodnota": 2475.0
      },
      {
        "Rok": 2007,
        "Hodnota": 2588.0
      },
      {
        "Rok": 2008,
        "Hodnota": 2708.0
      },
      {
        "Rok": 2009,
        "Hodnota": 2407.0
      },
      {
        "Rok": 2010,
        "Hodnota": 2615.0
      },
      {
        "Rok": 2011,
        "Hodnota": 2807.0
      },
      {
        "Rok": 2012,
        "Hodnota": 2799.0
      },
      {
        "Rok": 2013,
        "Hodnota": 2679.0
      },
      {
        "Rok": 2014,
        "Hodnota": 2645.0
      },
      {
        "Rok": 2015,
        "Hodnota": 2741.0
      },
      {
        "Rok": 2016,
        "Hodnota": 2910.0
      },
      {
        "Rok": 2017,
        "Hodnota": 2966.0
      },
      {
        "Rok": 2018,
        "Hodnota": 2924.0
      },
      {
        "Rok": 2019,
        "Hodnota": 3064.0
      },
      {
        "Rok": 2020,
        "Hodnota": 2880.0
      },
      {
        "Rok": 2021,
        "Hodnota": 2809.0
      },
      {
        "Rok": 2022,
        "Hodnota": 2263.0
      },
      {
        "Rok": 2023,
        "Hodnota": 2464.0
      },
      {
        "Rok": 2024,
        "Hodnota": 2402.0
      }
    ]
  },
  {
    "country": "Polsko",
    "data": [
      {
        "Rok": 2002,
        "Hodnota": 1286.0
      },
      {
        "Rok": 2003,
        "Hodnota": 1412.0
      },
      {
        "Rok": 2004,
        "Hodnota": 1482.0
      },
      {
        "Rok": 2005,
        "Hodnota": 1415.0
      },
      {
        "Rok": 2006,
        "Hodnota": 1454.0
      },
      {
        "Rok": 2007,
        "Hodnota": 1594.0
      },
      {
        "Rok": 2008,
        "Hodnota": 1609.0
      },
      {
        "Rok": 2009,
        "Hodnota": 1410.0
      },
      {
        "Rok": 2010,
        "Hodnota": 1699.0
      },
      {
        "Rok": 2011,
        "Hodnota": 1884.0
      },
      {
        "Rok": 2012,
        "Hodnota": 1778.0
      },
      {
        "Rok": 2013,
        "Hodnota": 1690.0
      },
      {
        "Rok": 2014,
        "Hodnota": 1816.0
      },
      {
        "Rok": 2015,
        "Hodnota": 1900.0
      },
      {
        "Rok": 2016,
        "Hodnota": 1964.0
      },
      {
        "Rok": 2017,
        "Hodnota": 2128.0
      },
      {
        "Rok": 2018,
        "Hodnota": 2481.0
      },
      {
        "Rok": 2019,
        "Hodnota": 2407.0
      },
      {
        "Rok": 2020,
        "Hodnota": 2218.0
      },
      {
        "Rok": 2021,
        "Hodnota": 2218.0
      },
      {
        "Rok": 2022,
        "Hodnota": 2377.0
      },
      {
        "Rok": 2023,
        "Hodnota": 2192.0
      },
      {
        "Rok": 2024,
        "Hodnota": 2119.0
      }
    ]
  },
  {
    "country": "Portugalsko",
    "data": [
      {
        "Rok": 2002,
        "Hodnota": 2729.0
      },
      {
        "Rok": 2003,
        "Hodnota": 2714.0
      },
      {
        "Rok": 2004,
        "Hodnota": 2826.0
      },
      {
        "Rok": 2005,
        "Hodnota": 2955.0
      },
      {
        "Rok": 2006,
        "Hodnota": 3024.0
      },
      {
        "Rok": 2007,
        "Hodnota": 3005.0
      },
      {
        "Rok": 2008,
        "Hodnota": 2826.0
      },
      {
        "Rok": 2009,
        "Hodnota": 2551.0
      },
      {
        "Rok": 2010,
        "Hodnota": 2511.0
      },
      {
        "Rok": 2011,
        "Hodnota": 2478.0
      },
      {
        "Rok": 2012,
        "Hodnota": 2485.0
      },
      {
        "Rok": 2013,
        "Hodnota": 2527.0
      },
      {
        "Rok": 2014,
        "Hodnota": 2465.0
      },
      {
        "Rok": 2015,
        "Hodnota": 2871.0
      },
      {
        "Rok": 2016,
        "Hodnota": 2885.0
      },
      {
        "Rok": 2017,
        "Hodnota": 3142.0
      },
      {
        "Rok": 2018,
        "Hodnota": 3013.0
      },
      {
        "Rok": 2019,
        "Hodnota": 3018.0
      },
      {
        "Rok": 2020,
        "Hodnota": 2533.0
      },
      {
        "Rok": 2021,
        "Hodnota": 2701.0
      },
      {
        "Rok": 2022,
        "Hodnota": 2836.0
      },
      {
        "Rok": 2023,
        "Hodnota": 2607.0
      },
      {
        "Rok": 2024,
        "Hodnota": 2703.0
      }
    ]
  },
  {
    "country": "Rumunsko",
    "data": [
      {
        "Rok": 2002,
        "Hodnota": 1314.0
      },
      {
        "Rok": 2003,
        "Hodnota": 1504.0
      },
      {
        "Rok": 2004,
        "Hodnota": 1688.0
      },
      {
        "Rok": 2005,
        "Hodnota": 1688.0
      },
      {
        "Rok": 2006,
        "Hodnota": 1683.0
      },
      {
        "Rok": 2007,
        "Hodnota": 1580.0
      },
      {
        "Rok": 2008,
        "Hodnota": 1454.0
      },
      {
        "Rok": 2009,
        "Hodnota": 900.0
      },
      {
        "Rok": 2010,
        "Hodnota": 991.0
      },
      {
        "Rok": 2011,
        "Hodnota": 998.0
      },
      {
        "Rok": 2012,
        "Hodnota": 943.0
      },
      {
        "Rok": 2013,
        "Hodnota": 994.0
      },
      {
        "Rok": 2014,
        "Hodnota": 1079.0
      },
      {
        "Rok": 2015,
        "Hodnota": 1209.0
      },
      {
        "Rok": 2016,
        "Hodnota": 1335.0
      },
      {
        "Rok": 2017,
        "Hodnota": 1356.0
      },
      {
        "Rok": 2018,
        "Hodnota": 1437.0
      },
      {
        "Rok": 2019,
        "Hodnota": 1464.0
      },
      {
        "Rok": 2020,
        "Hodnota": 1342.0
      },
      {
        "Rok": 2021,
        "Hodnota": 1588.0
      },
      {
        "Rok": 2022,
        "Hodnota": 1591.0
      },
      {
        "Rok": 2023,
        "Hodnota": 1342.0
      },
      {
        "Rok": 2024,
        "Hodnota": 1421.0
      }
    ]
  },
  {
    "country": "Slovinsko",
    "data": [
      {
        "Rok": 2002,
        "Hodnota": 1391.0
      },
      {
        "Rok": 2003,
        "Hodnota": 1575.0
      },
      {
        "Rok": 2004,
        "Hodnota": 1597.0
      },
      {
        "Rok": 2005,
        "Hodnota": 1869.0
      },
      {
        "Rok": 2006,
        "Hodnota": 2213.0
      },
      {
        "Rok": 2007,
        "Hodnota": 2481.0
      },
      {
        "Rok": 2008,
        "Hodnota": 2954.0
      },
      {
        "Rok": 2009,
        "Hodnota": 2618.0
      },
      {
        "Rok": 2010,
        "Hodnota": 3093.0
      },
      {
        "Rok": 2011,
        "Hodnota": 3269.0
      },
      {
        "Rok": 2012,
        "Hodnota": 3185.0
      },
      {
        "Rok": 2013,
        "Hodnota": 3294.0
      },
      {
        "Rok": 2014,
        "Hodnota": 3226.0
      },
      {
        "Rok": 2015,
        "Hodnota": 3223.0
      },
      {
        "Rok": 2016,
        "Hodnota": 3351.0
      },
      {
        "Rok": 2017,
        "Hodnota": 3739.0
      },
      {
        "Rok": 2018,
        "Hodnota": 4179.0
      },
      {
        "Rok": 2019,
        "Hodnota": 4222.0
      },
      {
        "Rok": 2020,
        "Hodnota": 3839.0
      },
      {
        "Rok": 2021,
        "Hodnota": 4192.0
      },
      {
        "Rok": 2022,
        "Hodnota": 5195.0
      },
      {
        "Rok": 2023,
        "Hodnota": 5075.0
      },
      {
        "Rok": 2024,
        "Hodnota": 5070.0
      }
    ]
  },
  {
    "country": "Slovensko",
    "data": [
      {
        "Rok": 2002,
        "Hodnota": 3655.0
      },
      {
        "Rok": 2003,
        "Hodnota": 3812.0
      },
      {
        "Rok": 2004,
        "Hodnota": 3967.0
      },
      {
        "Rok": 2005,
        "Hodnota": 3889.0
      },
      {
        "Rok": 2006,
        "Hodnota": 3997.0
      },
      {
        "Rok": 2007,
        "Hodnota": 4052.0
      },
      {
        "Rok": 2008,
        "Hodnota": 3871.0
      },
      {
        "Rok": 2009,
        "Hodnota": 3407.0
      },
      {
        "Rok": 2010,
        "Hodnota": 3640.0
      },
      {
        "Rok": 2011,
        "Hodnota": 3789.0
      },
      {
        "Rok": 2012,
        "Hodnota": 3533.0
      },
      {
        "Rok": 2013,
        "Hodnota": 3767.0
      },
      {
        "Rok": 2014,
        "Hodnota": 3532.0
      },
      {
        "Rok": 2015,
        "Hodnota": 3422.0
      },
      {
        "Rok": 2016,
        "Hodnota": 3388.0
      },
      {
        "Rok": 2017,
        "Hodnota": 3389.0
      },
      {
        "Rok": 2018,
        "Hodnota": 3616.0
      },
      {
        "Rok": 2019,
        "Hodnota": 3245.0
      },
      {
        "Rok": 2020,
        "Hodnota": 3051.0
      },
      {
        "Rok": 2021,
        "Hodnota": 3397.0
      },
      {
        "Rok": 2022,
        "Hodnota": 3110.0
      },
      {
        "Rok": 2023,
        "Hodnota": 3132.0
      },
      {
        "Rok": 2024,
        "Hodnota": 2842.0
      }
    ]
  },
  {
    "country": "Finsko",
    "data": [
      {
        "Rok": 2002,
        "Hodnota": 6935.0
      },
      {
        "Rok": 2003,
        "Hodnota": 7998.0
      },
      {
        "Rok": 2004,
        "Hodnota": 7900.0
      },
      {
        "Rok": 2005,
        "Hodnota": 7514.0
      },
      {
        "Rok": 2006,
        "Hodnota": 8037.0
      },
      {
        "Rok": 2007,
        "Hodnota": 7824.0
      },
      {
        "Rok": 2008,
        "Hodnota": 7832.0
      },
      {
        "Rok": 2009,
        "Hodnota": 6209.0
      },
      {
        "Rok": 2010,
        "Hodnota": 6573.0
      },
      {
        "Rok": 2011,
        "Hodnota": 6837.0
      },
      {
        "Rok": 2012,
        "Hodnota": 6079.0
      },
      {
        "Rok": 2013,
        "Hodnota": 6399.0
      },
      {
        "Rok": 2014,
        "Hodnota": 6369.0
      },
      {
        "Rok": 2015,
        "Hodnota": 5780.0
      },
      {
        "Rok": 2016,
        "Hodnota": 6419.0
      },
      {
        "Rok": 2017,
        "Hodnota": 6310.0
      },
      {
        "Rok": 2018,
        "Hodnota": 6480.0
      },
      {
        "Rok": 2019,
        "Hodnota": 6155.0
      },
      {
        "Rok": 2020,
        "Hodnota": 5778.0
      },
      {
        "Rok": 2021,
        "Hodnota": 5218.0
      },
      {
        "Rok": 2022,
        "Hodnota": 4403.0
      },
      {
        "Rok": 2023,
        "Hodnota": 3457.0
      },
      {
        "Rok": 2024,
        "Hodnota": 3417.0
      }
    ]
  },
  {
    "country": "Švédsko",
    "data": [
      {
        "Rok": 2002,
        "Hodnota": 3206.0
      },
      {
        "Rok": 2003,
        "Hodnota": 3363.0
      },
      {
        "Rok": 2004,
        "Hodnota": 3400.0
      },
      {
        "Rok": 2005,
        "Hodnota": 3413.0
      },
      {
        "Rok": 2006,
        "Hodnota": 3329.0
      },
      {
        "Rok": 2007,
        "Hodnota": 3407.0
      },
      {
        "Rok": 2008,
        "Hodnota": 3581.0
      },
      {
        "Rok": 2009,
        "Hodnota": 3169.0
      },
      {
        "Rok": 2010,
        "Hodnota": 3719.0
      },
      {
        "Rok": 2011,
        "Hodnota": 3660.0
      },
      {
        "Rok": 2012,
        "Hodnota": 3751.0
      },
      {
        "Rok": 2013,
        "Hodnota": 3519.0
      },
      {
        "Rok": 2014,
        "Hodnota": 3946.0
      },
      {
        "Rok": 2015,
        "Hodnota": 3988.0
      },
      {
        "Rok": 2016,
        "Hodnota": 4171.0
      },
      {
        "Rok": 2017,
        "Hodnota": 4197.0
      },
      {
        "Rok": 2018,
        "Hodnota": 4351.0
      },
      {
        "Rok": 2019,
        "Hodnota": 4062.0
      },
      {
        "Rok": 2020,
        "Hodnota": 3926.0
      },
      {
        "Rok": 2021,
        "Hodnota": 3971.0
      },
      {
        "Rok": 2022,
        "Hodnota": 4025.0
      },
      {
        "Rok": 2023,
        "Hodnota": 3830.0
      },
      {
        "Rok": 2024,
        "Hodnota": 3910.0
      }
    ]
  }
]
